ru_mvd_search_wanted/__init__.py
ru_mvd_search_wanted/asynchr.py
ru_mvd_search_wanted/exceptions.py
ru_mvd_search_wanted/settings.py
ru_mvd_search_wanted/sync.py
tests/__init__.py
tests/test_async.py
tests/test_sync.py
ru_mvd_search_wanted-0.0.4.dist-info/LICENSE
ru_mvd_search_wanted-0.0.4.dist-info/METADATA
ru_mvd_search_wanted-0.0.4.dist-info/WHEEL
ru_mvd_search_wanted-0.0.4.dist-info/top_level.txt
ru_mvd_search_wanted-0.0.4.dist-info/RECORD
