Metadata-Version: 2.1
Name: ru-mvd-search-wanted
Version: 0.0.4
Summary: Parser of information from the website of the Ministry of Internal Affairs Search
Home-page: https://github.com/daniilak/ru_mvd_search_wanted
Author: Daniil Agniashvili
Author-email: dortos123456@gmail.com
Classifier: Programming Language :: Python :: 3
Classifier: License :: OSI Approved :: MIT License
Classifier: Operating System :: Microsoft :: Windows
Classifier: Operating System :: POSIX :: Linux
Requires-Python: >3.7
License-File: LICENSE
Requires-Dist: httpx
Requires-Dist: beautifulsoup4
Requires-Dist: pip-system-certs
Requires-Dist: fake-useragent
